MANIFEST.in
readme.md
setup.py
lab6.egg-info/PKG-INFO
lab6.egg-info/SOURCES.txt
lab6.egg-info/dependency_links.txt
lab6.egg-info/entry_points.txt
lab6.egg-info/top_level.txt
package/__init__.py
package/__main__.py
package/empty.py
package/end.py
package/finish.py
package/selection_sort.py